[
  {
    "id": "visual-inspection",
    "type": "section",
    "title": "Visual Inspection",
    "description": "General condition assessment, component inspection, and anomaly documentation",
    "icon": "EyeOutlined",
    "order": 3,
    "size": 12
  },
  {
    "id": "overall-assessment-group",
    "type": "group",
    "title": "Overall Assessment",
    "description": "General visual inspection assessment",
    "sectionId": "visual-inspection",
    "order": 1,
    "size": 24,
    "collapsible": false
  },
  {
    "id": "overall-condition",
    "type": "select",
    "title": "Overall Condition",
    "label": "Overall Condition",
    "placeholder": "Select overall condition",
    "required": true,
    "size": 24,
    "sectionId": "visual-inspection",
    "groupId": "overall-assessment-group",
    "defaultValue": "",
    "options": [
      {"label": "Excellent", "value": "excellent"},
      {"label": "Good", "value": "good"},
      {"label": "Fair", "value": "fair"},
      {"label": "Poor", "value": "poor"},
      {"label": "Critical", "value": "critical"}
    ]
  },

  {
    "id": "weld-assessment-group",
    "type": "group",
    "title": "Weld Assessment",
    "description": "Weld condition and quality inspection findings",
    "sectionId": "visual-inspection",
    "order": 2,
    "size": 12,
    "collapsible": true,
    "watchField": "inspection-type",
    "showWhen": "internal,external,hot-work,high-pressure,high-temperature,combined"
  },
  {
    "id": "weld-condition",
    "type": "select",
    "title": "Weld Condition",
    "label": "Weld Condition",
    "placeholder": "Select weld condition",
    "size": 24,
    "sectionId": "visual-inspection",
    "groupId": "weld-assessment-group",
    "defaultValue": "",
    "options": [
      {"label": "Excellent", "value": "excellent"},
      {"label": "Good", "value": "good"},
      {"label": "Fair", "value": "fair"},
      {"label": "Poor", "value": "poor"},
      {"label": "Not Applicable", "value": "na"}
    ]
  },
  {
    "id": "weld-condition-findings",
    "type": "inspection-findings",
    "title": "Weld Condition Findings",
    "label": "Document weld condition findings with images and details",
    "size": 24,
    "sectionId": "visual-inspection",
    "groupId": "weld-assessment-group",
    "defaultValue": [],
    "watchField": "weld-condition",
    "showWhen": "fair,poor",
    "maxFindings": 10,
    "maxImagesPerFinding": 5,
    "showMeasurements": true,
    "showLocation": true,
    "showSeverity": true
  },
  {
    "id": "corrosion-assessment-group",
    "type": "group",
    "title": "Corrosion Assessment",
    "description": "Corrosion and rust inspection findings",
    "sectionId": "visual-inspection",
    "order": 3,
    "size": 12,
    "collapsible": true,
    "watchField": "inspection-type",
    "showWhen": "internal,confined-space,external,combined"
  },
  {
    "id": "corrosion-observed",
    "type": "radio",
    "title": "Corrosion Observed",
    "label": "Corrosion or rust observed",
    "size": 24,
    "sectionId": "visual-inspection",
    "groupId": "corrosion-assessment-group",
    "defaultValue": "no",
    "options": [
      {"label": "Yes", "value": "yes"},
      {"label": "No", "value": "no"}
    ]
  },
  {
    "id": "corrosion-findings",
    "type": "inspection-findings",
    "title": "Corrosion Findings",
    "label": "Document corrosion findings with images and details",
    "size": 24,
    "sectionId": "visual-inspection",
    "groupId": "corrosion-assessment-group",
    "defaultValue": [],
    "watchField": "corrosion-observed",
    "showWhen": "yes",
    "maxFindings": 10,
    "maxImagesPerFinding": 5,
    "showMeasurements": true,
    "showLocation": true,
    "showSeverity": true
  },
  {
    "id": "cracking-assessment-group",
    "type": "group",
    "title": "Cracking Assessment",
    "description": "Cracking and fracture inspection findings",
    "sectionId": "visual-inspection",
    "order": 4,
    "size": 12,
    "collapsible": true,
    "watchField": "inspection-type",
    "showWhen": "internal,external,hot-work,high-pressure,high-temperature,combined"
  },
  {
    "id": "cracking-observed",
    "type": "radio",
    "title": "Cracking Observed",
    "label": "Cracking or fractures observed",
    "size": 24,
    "sectionId": "visual-inspection",
    "groupId": "cracking-assessment-group",
    "defaultValue": "no",
    "options": [
      {"label": "Yes", "value": "yes"},
      {"label": "No", "value": "no"}
    ]
  },
  {
    "id": "cracking-findings",
    "type": "inspection-findings",
    "title": "Cracking Findings",
    "label": "Document cracking findings with images and details",
    "size": 24,
    "sectionId": "visual-inspection",
    "groupId": "cracking-assessment-group",
    "defaultValue": [],
    "watchField": "cracking-observed",
    "showWhen": "yes",
    "maxFindings": 10,
    "maxImagesPerFinding": 5,
    "showMeasurements": true,
    "showLocation": true,
    "showSeverity": true
  },
  {
    "id": "deformation-assessment-group",
    "type": "group",
    "title": "Deformation Assessment",
    "description": "Deformation and distortion inspection findings",
    "sectionId": "visual-inspection",
    "order": 5,
    "size": 12,
    "collapsible": true,
    "watchField": "inspection-type",
    "showWhen": "internal,external,high-pressure,high-temperature,combined"
  },
  {
    "id": "deformation-observed",
    "type": "radio",
    "title": "Deformation Observed",
    "label": "Deformation or distortion observed",
    "size": 24,
    "sectionId": "visual-inspection",
    "groupId": "deformation-assessment-group",
    "defaultValue": "no",
    "options": [
      {"label": "Yes", "value": "yes"},
      {"label": "No", "value": "no"}
    ]
  },
  {
    "id": "deformation-findings",
    "type": "inspection-findings",
    "title": "Deformation Findings",
    "label": "Document deformation findings with images and details",
    "size": 24,
    "sectionId": "visual-inspection",
    "groupId": "deformation-assessment-group",
    "defaultValue": [],
    "watchField": "deformation-observed",
    "showWhen": "yes",
    "maxFindings": 10,
    "maxImagesPerFinding": 5,
    "showMeasurements": true,
    "showLocation": true,
    "showSeverity": true
  },
  {
    "id": "leakage-assessment-group",
    "type": "group",
    "title": "Leakage Assessment",
    "description": "Leakage and seepage inspection findings",
    "sectionId": "visual-inspection",
    "order": 6,
    "size": 12,
    "collapsible": true,
    "watchField": "inspection-type",
    "showWhen": "internal,external,high-pressure,combined"
  },
  {
    "id": "leakage-observed",
    "type": "radio",
    "title": "Leakage Observed",
    "label": "Leakage or seepage observed",
    "size": 24,
    "sectionId": "visual-inspection",
    "groupId": "leakage-assessment-group",
    "defaultValue": "no",
    "options": [
      {"label": "Yes", "value": "yes"},
      {"label": "No", "value": "no"}
    ]
  },
  {
    "id": "leakage-findings",
    "type": "inspection-findings",
    "title": "Leakage Findings",
    "label": "Document leakage findings with images and details",
    "size": 24,
    "sectionId": "visual-inspection",
    "groupId": "leakage-assessment-group",
    "defaultValue": [],
    "watchField": "leakage-observed",
    "showWhen": "yes",
    "maxFindings": 10,
    "maxImagesPerFinding": 5,
    "showMeasurements": true,
    "showLocation": true,
    "showSeverity": true
  },
  {
    "id": "external-inspection-group",
    "type": "group",
    "title": "External Surface Assessment",
    "description": "External surface condition, coatings, and structural elements",
    "sectionId": "visual-inspection",
    "order": 7,
    "size": 12,
    "collapsible": true,
    "watchField": "inspection-type",
    "showWhen": "external,combined"
  },
  {
    "id": "coating-condition",
    "type": "select",
    "title": "Coating Condition",
    "label": "External Coating Condition",
    "placeholder": "Select coating condition",
    "size": 24,
    "sectionId": "visual-inspection",
    "groupId": "external-inspection-group",
    "defaultValue": "",
    "options": [
      {"label": "Excellent", "value": "excellent"},
      {"label": "Good", "value": "good"},
      {"label": "Fair", "value": "fair"},
      {"label": "Poor", "value": "poor"},
      {"label": "Failed", "value": "failed"}
    ]
  },
  {
    "id": "coating-findings",
    "type": "inspection-findings",
    "title": "Coating Findings",
    "label": "Document coating condition findings with images and details",
    "size": 24,
    "sectionId": "visual-inspection",
    "groupId": "external-inspection-group",
    "defaultValue": [],
    "watchField": "coating-condition",
    "showWhen": "fair,poor,failed",
    "maxFindings": 10,
    "maxImagesPerFinding": 5,
    "showMeasurements": true,
    "showLocation": true,
    "showSeverity": true
  },
  {
    "id": "support-condition",
    "type": "select",
    "title": "Support Condition",
    "label": "Support Structure Condition",
    "placeholder": "Select support condition",
    "size": 24,
    "sectionId": "visual-inspection",
    "groupId": "external-inspection-group",
    "defaultValue": "",
    "options": [
      {"label": "Excellent", "value": "excellent"},
      {"label": "Good", "value": "good"},
      {"label": "Fair", "value": "fair"},
      {"label": "Poor", "value": "poor"},
      {"label": "Critical", "value": "critical"}
    ]
  },
  {
    "id": "support-findings",
    "type": "inspection-findings",
    "title": "Support Findings",
    "label": "Document support structure findings with images and details",
    "size": 24,
    "sectionId": "visual-inspection",
    "groupId": "external-inspection-group",
    "defaultValue": [],
    "watchField": "support-condition",
    "showWhen": "fair,poor,critical",
    "maxFindings": 10,
    "maxImagesPerFinding": 5,
    "showMeasurements": true,
    "showLocation": true,
    "showSeverity": true
  },
  {
    "id": "hot-work-inspection-group",
    "type": "group",
    "title": "Hot Work Area Assessment",
    "description": "Heat-affected zones and weld area inspection",
    "sectionId": "visual-inspection",
    "order": 8,
    "size": 12,
    "collapsible": true,
    "watchField": "inspection-type",
    "showWhen": "hot-work,combined"
  },
  {
    "id": "heat-affected-zone",
    "type": "radio",
    "title": "Heat Affected Zone",
    "label": "Heat affected zone visible or suspected",
    "size": 24,
    "sectionId": "visual-inspection",
    "groupId": "hot-work-inspection-group",
    "defaultValue": "no",
    "options": [
      {"label": "Yes", "value": "yes"},
      {"label": "No", "value": "no"}
    ]
  },
  {
    "id": "heat-affected-findings",
    "type": "inspection-findings",
    "title": "Heat Affected Zone Findings",
    "label": "Document heat affected zone findings with images and details",
    "size": 24,
    "sectionId": "visual-inspection",
    "groupId": "hot-work-inspection-group",
    "defaultValue": [],
    "watchField": "heat-affected-zone",
    "showWhen": "yes",
    "maxFindings": 10,
    "maxImagesPerFinding": 5,
    "showMeasurements": true,
    "showLocation": true,
    "showSeverity": true
  },
  {
    "id": "weld-quality",
    "type": "select",
    "title": "Weld Quality",
    "label": "Weld Quality Assessment",
    "placeholder": "Select weld quality",
    "size": 24,
    "sectionId": "visual-inspection",
    "groupId": "hot-work-inspection-group",
    "defaultValue": "",
    "options": [
      {"label": "Excellent", "value": "excellent"},
      {"label": "Good", "value": "good"},
      {"label": "Fair", "value": "fair"},
      {"label": "Poor", "value": "poor"},
      {"label": "Defective", "value": "defective"}
    ]
  },
  {
    "id": "weld-quality-findings",
    "type": "inspection-findings",
    "title": "Weld Quality Findings",
    "label": "Document weld quality findings with images and details",
    "size": 24,
    "sectionId": "visual-inspection",
    "groupId": "hot-work-inspection-group",
    "defaultValue": [],
    "watchField": "weld-quality",
    "showWhen": "fair,poor,defective",
    "maxFindings": 10,
    "maxImagesPerFinding": 5,
    "showMeasurements": true,
    "showLocation": true,
    "showSeverity": true
  },
  {
    "id": "high-pressure-inspection-group",
    "type": "group",
    "title": "High Pressure System Assessment",
    "description": "Pressure-related damage and stress concentration areas",
    "sectionId": "visual-inspection",
    "order": 9,
    "size": 12,
    "collapsible": true,
    "watchField": "inspection-type",
    "showWhen": "high-pressure,combined"
  },
  {
    "id": "stress-concentration",
    "type": "radio",
    "title": "Stress Concentration",
    "label": "Stress concentration areas identified",
    "size": 24,
    "sectionId": "visual-inspection",
    "groupId": "high-pressure-inspection-group",
    "defaultValue": "no",
    "options": [
      {"label": "Yes", "value": "yes"},
      {"label": "No", "value": "no"}
    ]
  },
  {
    "id": "stress-concentration-findings",
    "type": "inspection-findings",
    "title": "Stress Concentration Findings",
    "label": "Document stress concentration findings with images and details",
    "size": 24,
    "sectionId": "visual-inspection",
    "groupId": "high-pressure-inspection-group",
    "defaultValue": [],
    "watchField": "stress-concentration",
    "showWhen": "yes",
    "maxFindings": 10,
    "maxImagesPerFinding": 5,
    "showMeasurements": true,
    "showLocation": true,
    "showSeverity": true
  },
  {
    "id": "pressure-vessel-integrity",
    "type": "select",
    "title": "Pressure Vessel Integrity",
    "label": "Pressure Vessel Structural Integrity",
    "placeholder": "Select integrity condition",
    "size": 24,
    "sectionId": "visual-inspection",
    "groupId": "high-pressure-inspection-group",
    "defaultValue": "",
    "options": [
      {"label": "Excellent", "value": "excellent"},
      {"label": "Good", "value": "good"},
      {"label": "Fair", "value": "fair"},
      {"label": "Poor", "value": "poor"},
      {"label": "Critical", "value": "critical"}
    ]
  },
  {
    "id": "high-temperature-inspection-group",
    "type": "group",
    "title": "High Temperature System Assessment",
    "description": "Thermal damage and creep effects",
    "sectionId": "visual-inspection",
    "order": 10,
    "size": 12,
    "collapsible": true,
    "watchField": "inspection-type",
    "showWhen": "high-temperature,combined"
  },
  {
    "id": "thermal-damage",
    "type": "radio",
    "title": "Thermal Damage",
    "label": "Thermal damage or creep effects observed",
    "size": 24,
    "sectionId": "visual-inspection",
    "groupId": "high-temperature-inspection-group",
    "defaultValue": "no",
    "options": [
      {"label": "Yes", "value": "yes"},
      {"label": "No", "value": "no"}
    ]
  },
  {
    "id": "thermal-damage-findings",
    "type": "inspection-findings",
    "title": "Thermal Damage Findings",
    "label": "Document thermal damage findings with images and details",
    "size": 24,
    "sectionId": "visual-inspection",
    "groupId": "high-temperature-inspection-group",
    "defaultValue": [],
    "watchField": "thermal-damage",
    "showWhen": "yes",
    "maxFindings": 10,
    "maxImagesPerFinding": 5,
    "showMeasurements": true,
    "showLocation": true,
    "showSeverity": true
  },
  {
    "id": "creep-effects",
    "type": "radio",
    "title": "Creep Effects",
    "label": "Creep effects or material degradation observed",
    "size": 24,
    "sectionId": "visual-inspection",
    "groupId": "high-temperature-inspection-group",
    "defaultValue": "no",
    "options": [
      {"label": "Yes", "value": "yes"},
      {"label": "No", "value": "no"}
    ]
  },
  {
    "id": "creep-effects-findings",
    "type": "inspection-findings",
    "title": "Creep Effects Findings",
    "label": "Document creep effects findings with images and details",
    "size": 24,
    "sectionId": "visual-inspection",
    "groupId": "high-temperature-inspection-group",
    "defaultValue": [],
    "watchField": "creep-effects",
    "showWhen": "yes",
    "maxFindings": 10,
    "maxImagesPerFinding": 5,
    "showMeasurements": true,
    "showLocation": true,
    "showSeverity": true
  },
  {
    "id": "confined-space-inspection-group",
    "type": "group",
    "title": "Confined Space Assessment",
    "description": "Internal confined space conditions and access points",
    "sectionId": "visual-inspection",
    "order": 11,
    "size": 12,
    "collapsible": true,
    "watchField": "inspection-type",
    "showWhen": "confined-space,combined"
  },
  {
    "id": "elevated-work-inspection-group",
    "type": "group",
    "title": "Elevated Work Assessment",
    "description": "Elevated work area conditions and access safety",
    "sectionId": "visual-inspection",
    "order": 12,
    "size": 12,
    "collapsible": true,
    "watchField": "inspection-type",
    "showWhen": "elevated,combined"
  },
  {
    "id": "access-equipment-condition",
    "type": "select",
    "title": "Access Equipment Condition",
    "label": "Access Equipment Condition",
    "placeholder": "Select access equipment condition",
    "size": 24,
    "sectionId": "visual-inspection",
    "groupId": "elevated-work-inspection-group",
    "defaultValue": "",
    "options": [
      {"label": "Excellent", "value": "excellent"},
      {"label": "Good", "value": "good"},
      {"label": "Fair", "value": "fair"},
      {"label": "Poor", "value": "poor"},
      {"label": "Unsafe", "value": "unsafe"}
    ]
  },
  {
    "id": "work-platform-stability",
    "type": "radio",
    "title": "Work Platform Stability",
    "label": "Work platform or scaffolding is stable and secure",
    "size": 24,
    "sectionId": "visual-inspection",
    "groupId": "elevated-work-inspection-group",
    "defaultValue": "no",
    "options": [
      {"label": "Yes", "value": "yes"},
      {"label": "No", "value": "no"}
    ]
  },
  {
    "id": "elevated-work-findings",
    "type": "inspection-findings",
    "title": "Elevated Work Findings",
    "label": "Document elevated work area findings with images and details",
    "size": 24,
    "sectionId": "visual-inspection",
    "groupId": "elevated-work-inspection-group",
    "defaultValue": [],
    "watchField": "work-platform-stability",
    "showWhen": "no",
    "maxFindings": 10,
    "maxImagesPerFinding": 5,
    "showMeasurements": true,
    "showLocation": true,
    "showSeverity": true
  },
  {
    "id": "access-point-condition",
    "type": "select",
    "title": "Access Point Condition",
    "label": "Access Point Condition",
    "placeholder": "Select access point condition",
    "size": 24,
    "sectionId": "visual-inspection",
    "groupId": "confined-space-inspection-group",
    "defaultValue": "",
    "options": [
      {"label": "Excellent", "value": "excellent"},
      {"label": "Good", "value": "good"},
      {"label": "Fair", "value": "fair"},
      {"label": "Poor", "value": "poor"},
      {"label": "Hazardous", "value": "hazardous"}
    ]
  },
  {
    "id": "internal-atmosphere",
    "type": "radio",
    "title": "Internal Atmosphere",
    "label": "Internal atmosphere conditions acceptable",
    "size": 24,
    "sectionId": "visual-inspection",
    "groupId": "confined-space-inspection-group",
    "defaultValue": "no",
    "options": [
      {"label": "Yes", "value": "yes"},
      {"label": "No", "value": "no"}
    ]
  },
  {
    "id": "internal-atmosphere-findings",
    "type": "inspection-findings",
    "title": "Internal Atmosphere Findings",
    "label": "Document internal atmosphere findings with images and details",
    "size": 24,
    "sectionId": "visual-inspection",
    "groupId": "confined-space-inspection-group",
    "defaultValue": [],
    "watchField": "internal-atmosphere",
    "showWhen": "no",
    "maxFindings": 10,
    "maxImagesPerFinding": 5,
    "showMeasurements": true,
    "showLocation": true,
    "showSeverity": true
  },
  {
    "id": "general-notes-group",
    "type": "group",
    "title": "General Notes",
    "description": "Additional observations and notes",
    "sectionId": "visual-inspection",
    "order": 13,
    "size": 24,
    "collapsible": false
  },
  {
    "id": "visual-notes",
    "type": "textarea",
    "title": "Visual Inspection Notes",
    "label": "Additional observations and notes",
    "placeholder": "Enter detailed observations and findings",
    "size": 24,
    "sectionId": "visual-inspection",
    "groupId": "general-notes-group",
    "defaultValue": ""
  }
] 